{
  "group": "nether_avoider",
  "type": "minecraft:crafting_shaped",
  "pattern": [
    " 1 ",
    "345",
    " 7 "
  ],
  "key": {
    "1": {
      "item": "minecraft:skull",
      "data": 1
    },
    "3": {
      "item": "minecraft:skull",
      "data": 1
    },
    "4": {
      "item": "wobr:glowing_obsidian"
    },
    "5": {
      "item": "minecraft:skull",
      "data": 1
    },
    "7": {
      "item": "minecraft:ender_eye"
    }
  },
  "result": {
    "item": "wobr:nether_avoider_inactive",
    "count": 1
  }
}